{"expireTime":9007200930494308000,"key":"transformer-remark-markdown-ast-cd759dfbb141a72f4df5338e2ac2afd3-gatsby-remark-external-linksgatsby-remark-imagesgatsby-remark-code-titlesgatsby-remark-prismjs-","val":{"type":"root","children":[{"type":"paragraph","children":[{"type":"text","value":"Hello! I'm Hufaid Khan, i'm based in Abbottabad, Pakistan.","position":{"start":{"line":2,"column":1,"offset":1},"end":{"line":2,"column":59,"offset":59},"indent":[]}}],"position":{"start":{"line":2,"column":1,"offset":1},"end":{"line":2,"column":59,"offset":59},"indent":[]}},{"type":"paragraph","children":[{"type":"text","value":"I'm a multi-skilled professional with 3+ years of experience in WordPress development, Frontend development technical support, customer care, and virtual assistance. I can develop custom themes, troubleshoot technical issues, provide excellent customer service, and handle administrative tasks efficiently. I have strong communication and problem-solving skills and a passion for delivering quality results.","position":{"start":{"line":4,"column":1,"offset":61},"end":{"line":4,"column":408,"offset":468},"indent":[]}}],"position":{"start":{"line":4,"column":1,"offset":61},"end":{"line":4,"column":408,"offset":468},"indent":[]}},{"type":"paragraph","children":[{"type":"text","value":"Here are a few of the other activities that I love to do!","position":{"start":{"line":8,"column":1,"offset":472},"end":{"line":8,"column":58,"offset":529},"indent":[]}}],"position":{"start":{"line":8,"column":1,"offset":472},"end":{"line":8,"column":58,"offset":529},"indent":[]}}],"position":{"start":{"line":1,"column":1,"offset":0},"end":{"line":9,"column":1,"offset":530}}}}